deploy_box_cli/__init__.py
deploy_box_cli/cli.py
deploy_box_cli/helpers/__init__.py
deploy_box_cli/helpers/auth_helper.py
deploy_box_cli/helpers/deployment_helper.py
deploy_box_cli/helpers/docker_helper.py
deploy_box_cli/helpers/gcp_helper.py
deploy_box_cli/helpers/menu_helper.py
deploy_box_cli/helpers/decorators/__init__.py
deploy_box_cli/helpers/decorators/singleton.py
deploy_box_cli-0.1.10.dist-info/METADATA
deploy_box_cli-0.1.10.dist-info/WHEEL
deploy_box_cli-0.1.10.dist-info/entry_points.txt
deploy_box_cli-0.1.10.dist-info/top_level.txt
deploy_box_cli-0.1.10.dist-info/RECORD
