Metadata-Version: 2.1
Name: deploy-box-cli
Version: 0.1.10
Summary: CLI for managing Deploy Box operations
Author: Jacob Wernke
Author-email: Wernke.jacob@gmail.com
Classifier: Programming Language :: Python :: 3
Classifier: License :: OSI Approved :: MIT License
Classifier: Operating System :: OS Independent
Requires-Dist: requests
Requires-Dist: pkce
Requires-Dist: keyring
Requires-Dist: readchar
Requires-Dist: arrow==1.3.0
Requires-Dist: asgiref==3.8.1
Requires-Dist: binaryornot==0.4.4
Requires-Dist: cachetools==5.5.2
Requires-Dist: certifi==2025.1.31
Requires-Dist: cffi==1.17.1
Requires-Dist: chardet==5.2.0
Requires-Dist: charset-normalizer==3.4.1
Requires-Dist: click==8.1.8
Requires-Dist: colorama==0.4.6
Requires-Dist: cookiecutter==2.6.0
Requires-Dist: cryptography==44.0.2
Requires-Dist: Django==5.1.6
Requires-Dist: django-browser-reload==1.18.0
Requires-Dist: django-environ==0.12.0
Requires-Dist: django-oauth-toolkit==3.0.1
Requires-Dist: django-tailwind==3.8.0
Requires-Dist: django-webpack-loader==3.1.1
Requires-Dist: djangorestframework==3.15.2
Requires-Dist: djangorestframework-simplejwt==5.5.0
Requires-Dist: docker==7.1.0
Requires-Dist: google-api-core==2.24.2
Requires-Dist: google-auth==2.38.0
Requires-Dist: google-cloud-artifact-registry==1.15.1
Requires-Dist: google-cloud-core==2.4.3
Requires-Dist: google-cloud-storage==3.1.0
Requires-Dist: google-crc32c==1.6.0
Requires-Dist: google-resumable-media==2.7.2
Requires-Dist: googleapis-common-protos==1.69.1
Requires-Dist: grpc-google-iam-v1==0.14.1
Requires-Dist: grpcio==1.71.0
Requires-Dist: grpcio-status==1.71.0
Requires-Dist: idna==3.10
Requires-Dist: jaraco.classes==3.4.0
Requires-Dist: jaraco.context==6.0.1
Requires-Dist: jaraco.functools==4.1.0
Requires-Dist: Jinja2==3.1.5
Requires-Dist: jwcrypto==1.5.6
Requires-Dist: keyring==25.6.0
Requires-Dist: markdown-it-py==3.0.0
Requires-Dist: MarkupSafe==3.0.2
Requires-Dist: mdurl==0.1.2
Requires-Dist: more-itertools==10.6.0
Requires-Dist: oauthlib==3.2.2
Requires-Dist: pkce==1.0.3
Requires-Dist: proto-plus==1.26.1
Requires-Dist: protobuf==5.29.3
Requires-Dist: psycopg2==2.9.10
Requires-Dist: pyasn1==0.6.1
Requires-Dist: pyasn1-modules==0.4.1
Requires-Dist: pycparser==2.22
Requires-Dist: Pygments==2.19.1
Requires-Dist: PyJWT==2.9.0
Requires-Dist: python-dateutil==2.9.0.post0
Requires-Dist: python-dotenv==1.0.1
Requires-Dist: python-slugify==8.0.4
Requires-Dist: PyYAML==6.0.2
Requires-Dist: readchar==4.2.1
Requires-Dist: requests==2.32.3
Requires-Dist: rich==13.9.4
Requires-Dist: rsa==4.9
Requires-Dist: six==1.17.0
Requires-Dist: sqlparse==0.5.3
Requires-Dist: stripe==11.6.0
Requires-Dist: text-unidecode==1.3
Requires-Dist: types-python-dateutil==2.9.0.20241206
Requires-Dist: typing-extensions==4.12.2
Requires-Dist: tzdata==2025.1
Requires-Dist: urllib3==2.3.0
